{"version":1,"resource":"file:///d%3A/Coding/htmlcss/test10-Sass/index.html","entries":[{"id":"9749.html","timestamp":1761820584096},{"id":"8vUs.html","timestamp":1761822723627},{"id":"touN.html","timestamp":1761822755202},{"id":"ISS8.html","timestamp":1761822778565},{"id":"tUVM.html","timestamp":1761824568611},{"id":"jOKK.html","timestamp":1761824592988},{"id":"Ejto.html","timestamp":1761824604755},{"id":"HmWo.html","timestamp":1761824628602},{"id":"QNzw.html","timestamp":1761825290237},{"id":"VD8m.html","timestamp":1761825627572},{"id":"JBbJ.html","timestamp":1761825805981},{"id":"VXzD.html","timestamp":1761825849371},{"id":"Xxho.html","timestamp":1761825876729},{"id":"RsEI.html","timestamp":1761825923940},{"id":"wAyr.html","timestamp":1761826212063},{"id":"gnFH.html","timestamp":1761909689972},{"id":"Me0j.html","timestamp":1761909713926},{"id":"4uC9.html","timestamp":1761909751153},{"id":"o8Hd.html","timestamp":1761909772758},{"id":"8tW7.html","timestamp":1761909799991},{"id":"V5Js.html","timestamp":1761909832334},{"id":"zJfn.html","source":"undoRedo.source","timestamp":1761909837526},{"id":"oW12.html","timestamp":1761909856331},{"id":"USzl.html","timestamp":1761909869088},{"id":"QEs0.html","timestamp":1761909924076},{"id":"td2d.html","source":"undoRedo.source","timestamp":1761909940474},{"id":"DmY8.html","timestamp":1761909946338},{"id":"1f13.html","timestamp":1761909964547},{"id":"BpiK.html","timestamp":1761909979173},{"id":"zzVb.html","source":"undoRedo.source","timestamp":1761909989225},{"id":"KCxl.html","timestamp":1761909990750},{"id":"Oybd.html","timestamp":1761910041004},{"id":"Z9om.html","timestamp":1761910064291},{"id":"dWWF.html","timestamp":1761910079019},{"id":"5qhb.html","timestamp":1761910115557}]}