{"version":1,"resource":"file:///d%3A/Coding/javascripts/test07/index.html","entries":[{"id":"4Hm1.html","timestamp":1762088124233},{"id":"3b9t.html","timestamp":1762088801021},{"id":"RHMq.html","timestamp":1762088841051},{"id":"BrwQ.html","timestamp":1762088893988},{"id":"wGgn.html","timestamp":1762088924713},{"id":"8iRe.html","timestamp":1762088939229},{"id":"1DMz.html","timestamp":1762088990299},{"id":"XYRu.html","timestamp":1762089038880},{"id":"34y4.html","timestamp":1762089050086},{"id":"Muwy.html","timestamp":1762089119260},{"id":"rjQL.html","timestamp":1762089142574},{"id":"dkWU.html","timestamp":1762089156529},{"id":"Tbmf.html","timestamp":1762089204711},{"id":"0mq7.html","timestamp":1762089223697},{"id":"gbfT.html","timestamp":1762089270697},{"id":"TfBJ.html","timestamp":1762089301401},{"id":"EGgw.html","timestamp":1762089336885}]}